{
  "AirPods (2nd generation)": {
    "name": "AirPods (2nd generation)",
    "type": "AirPods",
    "order": 0,
    "hideChildren": true,
    "devices": [
      "AirPods2,1",
      "AirPods1,2"
    ]
  },
  "AirPods Pro": {
    "name": "AirPods Pro",
    "type": "AirPods",
    "order": 1,
    "hideChildren": true,
    "devices": [
      "AirPods2,2",
      "AirPodsPro1,1",
      "iProd8,1"
    ]
  },
  "AirPods Max": {
    "name": "AirPods Max",
    "type": "AirPods",
    "order": 2,
    "hideChildren": true,
    "devices": [
      "AirPodsMax1,1",
      "iProd8,6"
    ]
  },
  "AirPods (3rd generation)": {
    "name": "AirPods (3rd generation)",
    "type": "AirPods",
    "order": 3,
    "hideChildren": true,
    "devices": [
      "AirPods1,3",
      "Audio2,1"
    ]
  },
  "AirTag": {
    "name": "AirTag",
    "type": "AirTag",
    "hideChildren": true,
    "order": 0,
    "devices": [
      "AirTag1,1",
      "afw1,5"
    ]
  },
  "Apple TV (3rd generation)": {
    "name": "Apple TV (3rd generation)",
    "type": "Apple TV",
    "order": 0,
    "devices": [
      "AppleTV3,1",
      "AppleTV3,2"
    ],
    "hideChildren": false
  },
  "Apple Watch (1st generation)": {
    "name": "Apple Watch (1st generation)",
    "type": "Apple Watch",
    "order": 0,
    "devices": [
      "Watch1,1",
      "Watch1,2"
    ],
    "hideChildren": false
  },
  "Apple Watch Series 1": {
    "name": "Apple Watch Series 1",
    "type": "Apple Watch",
    "order": 1,
    "devices": [
      "Watch2,6",
      "Watch2,7"
    ],
    "hideChildren": false
  },
  "Apple Watch Series 2": {
    "name": "Apple Watch Series 2",
    "type": "Apple Watch",
    "order": 2,
    "devices": [
      "Watch2,3",
      "Watch2,4"
    ],
    "hideChildren": false
  },
  "Apple Watch Series 3": {
    "name": "Apple Watch Series 3",
    "type": "Apple Watch",
    "order": 3,
    "devices": [
      "Watch3,1",
      "Watch3,2",
      "Watch3,3",
      "Watch3,4"
    ],
    "hideChildren": false
  },
  "Apple Watch Series 4": {
    "name": "Apple Watch Series 4",
    "type": "Apple Watch",
    "order": 4,
    "devices": [
      "Watch4,1",
      "Watch4,2",
      "Watch4,3",
      "Watch4,4"
    ],
    "hideChildren": false
  },
  "Apple Watch Series 5": {
    "name": "Apple Watch Series 5",
    "type": "Apple Watch",
    "order": 5,
    "devices": [
      "Watch5,1",
      "Watch5,2",
      "Watch5,3",
      "Watch5,4"
    ],
    "hideChildren": false
  },
  "Apple Watch SE": {
    "name": "Apple Watch SE",
    "type": "Apple Watch",
    "order": 6,
    "devices": [
      "Watch5,9",
      "Watch5,10",
      "Watch5,11",
      "Watch5,12"
    ],
    "hideChildren": false
  },
  "Apple Watch Series 6": {
    "name": "Apple Watch Series 6",
    "type": "Apple Watch",
    "order": 7,
    "devices": [
      "Watch6,1",
      "Watch6,2",
      "Watch6,3",
      "Watch6,4"
    ],
    "hideChildren": false
  },
  "Apple Watch Series 7": {
    "name": "Apple Watch Series 7",
    "type": "Apple Watch",
    "order": 8,
    "devices": [
      "Watch6,6",
      "Watch6,7",
      "Watch6,8",
      "Watch6,9"
    ],
    "hideChildren": false
  },
  "Powerbeats (1st generation)": {
    "name": "Powerbeats (1st generation)",
    "type": "Beats Earbuds",
    "order": 0,
    "devices": [
      "Powerbeats (1st generation)",
      "Powerbeats (1st generation) Lebron James Edition"
    ],
    "hideChildren": false
  },
  "iBeats": {
    "name": "iBeats",
    "type": "Beats Earbuds",
    "order": 1,
    "devices": [
      "iBeats",
      "iBeats Justbeats"
    ],
    "hideChildren": false
  },
  "urBeats (1st generation)": {
    "name": "urBeats (1st generation)",
    "type": "Beats Earbuds",
    "order": 2,
    "devices": [
      "urBeats (1st generation)",
      "urBeats SE",
      "urBeats (1st generation) Hello Kitty Edition",
      "urBeats (1st generation) Alexander Wang Edition",
      "urBeats (1st generation) Paris Saint-Germain Edition",
      "urBeats (1st generation) Nicki Minaj Edition"
    ],
    "hideChildren": false
  },
  "Beats Tour²": {
    "name": "Beats Tour²",
    "type": "Beats Earbuds",
    "order": 3,
    "devices": [
      "Beats Tour2",
      "Beats Tour2 MCM Edition",
      "Beats Tour 2.5"
    ],
    "hideChildren": false
  },
  "Powerbeats² Wireless": {
    "name": "Powerbeats² Wireless",
    "type": "Beats Earbuds",
    "order": 4,
    "devices": [
      "Powerbeats2 Wireless",
      "Powerbeats2 Wireless UNDERCOVER Edition",
      "Powerbeats2 Wireless KITH Edition"
    ],
    "hideChildren": false
  },
  "Powerbeats³ Wireless": {
    "name": "Powerbeats³ Wireless",
    "type": "Beats Earbuds",
    "order": 5,
    "devices": [
      "PowerBeats3,1",
      "PowerBeats3,1-balmain"
    ],
    "hideChildren": false
  },
  "Beatsˣ": {
    "name": "Beatsˣ",
    "type": "Beats Earbuds",
    "order": 6,
    "devices": [
      "BeatsX1,1",
      "BeatsX1,1-sacai",
      "BeatsX1,1-undefeated"
    ],
    "hideChildren": false
  },
  "Powerbeats Pro": {
    "name": "Powerbeats Pro",
    "type": "Beats Earbuds",
    "order": 7,
    "devices": [
      "PowerbeatsPro1,1",
      "PowerbeatsPro1,1-nba",
      "PowerbeatsPro1,1-paria",
      "PowerbeatsPro1,1-faze",
      "PowerbeatsPro1,1-fragment",
      "PowerbeatsPro1,1-samuel"
    ],
    "hideChildren": false
  },
  "Powerbeats (4th generation)": {
    "name": "Powerbeats (4th generation)",
    "type": "Beats Earbuds",
    "order": 8,
    "devices": [
      "Powerbeats4,1",
      "Powerbeats4,1-ambush"
    ],
    "hideChildren": false
  },
  "Beats Flex": {
    "name": "Beats Flex",
    "type": "Beats Earbuds",
    "order": 9,
    "devices": [
      "Beats Flex",
      "Beats Flex fragment design Edition"
    ],
    "hideChildren": false
  },
  "Beats Studio Buds": {
    "name": "Beats Studio Buds",
    "type": "Beats Earbuds",
    "order": 10,
    "devices": [
      "Beats Studio Buds",
      "Beats Studio Buds Year of the Tiger Edition",
      "Beats Studio Buds Union Edition",
      "Beats Studio Buds Daily Paper Edition"
    ],
    "hideChildren": false
  },
  "Beats Studio (1st generation)": {
    "name": "Beats Studio (1st generation)",
    "type": "Beats Headphones",
    "order": 0,
    "devices": [
      "Beats Studio (1st generation)",
      "Beats Studio (1st generation) Illest Edition",
      "Beats Studio (1st generation) Selfridges Edition",
      "Beats Studio (1st generation) Nate Robinson Edition",
      "Beats Studio (1st generation) Harley Davidson Edition",
      "Beats Studio (1st generation) Staple Design Edition",
      "Beats Studio (1st generation) Maserati Edition",
      "Beats Studio (1st generation) Pigalle Edition",
      "Beats Studio (1st generation) Milkcrate Athletics Edition"
    ],
    "hideChildren": false
  },
  "Beats Solo HD": {
    "name": "Beats Solo HD",
    "type": "Beats Headphones",
    "order": 1,
    "devices": [
      "Beats Solo HD",
      "Beats Solo HD BAPE Edition",
      "Beats Solo HD Paris Saint-Germain Edition",
      "Beats Solo HD Futura Edition",
      "JustBeats Solo"
    ],
    "hideChildren": false
  },
  "Beats Pro": {
    "name": "Beats Pro",
    "type": "Beats Headphones",
    "order": 2,
    "devices": [
      "Beats Pro",
      "Beats Detox Pro",
      "Beats Pro Illest Edition",
      "Beats Pro Lamborghini Edition",
      "Beats Pro Lil Wayne Edition",
      "Beats Pro Fendi Edition",
      "Beats Pro Nicki Minaj Edition",
      "Beats Pro LeBron James MVP Edition"
    ],
    "hideChildren": false
  },
  "Beats Executive": {
    "name": "Beats Executive",
    "type": "Beats Headphones",
    "order": 3,
    "devices": [
      "Beats Executive",
      "Beats Executive colette Edition"
    ],
    "hideChildren": false
  },
  "Beats Studio (2nd generation)": {
    "name": "Beats Studio (2nd generation)",
    "type": "Beats Headphones",
    "devices": [
      "Beats Studio (2nd generation)",
      "Beats Studio (2nd generation) Chief Keef Edition"
    ],
    "hideChildren": false,
    "order": 4
  },
  "Beats Studio Wireless": {
    "name": "Beats Studio Wireless",
    "type": "Beats Headphones",
    "devices": [
      "Beats Studio Wireless",
      "Beats Studio Wireless Alexander Wang Edition",
      "Beats Studio Wireless Balmain Edition",
      "Beats Studio Wireless Ellen Edition",
      "Beats Studio Wireless Gloss Gold Edition",
      "Beats Studio Wireless KITH Edition",
      "Beats Studio Wireless MCM Edition",
      "Beats Studio Wireless Pigalle Edition",
      "Beats Studio Wireless Snarkitecture Edition",
      "Beats Studio Wireless UNKNWN Edition",
      "Beats Studio Wireless Unity Edition"
    ],
    "hideChildren": false,
    "order": 5
  },
  "Beats Solo²": {
    "name": "Beats Solo²",
    "type": "Beats Headphones",
    "order": 6,
    "devices": [
      "Beats Solo2",
      "Beats Solo2 Hello Kitty Edition",
      "Beats Solo2 fragment design Edition",
      "Beats Solo2 Chen Man - Year Of The Sheep Edition"
    ],
    "hideChildren": false
  },
  "Beats Solo² Wireless": {
    "name": "Beats Solo² Wireless",
    "type": "Beats Headphones",
    "order": 7,
    "devices": [
      "Beats Solo2 Wireless",
      "Beats Solo2 Wireless Year of the Monkey Edition",
      "Beats Solo2 Wireless MLB All-Star Edition"
    ],
    "hideChildren": false
  },
  "Beats Solo³ Wireless": {
    "name": "Beats Solo³ Wireless",
    "type": "Beats Headphones",
    "order": 8,
    "devices": [
      "BeatsSolo3,1",
      "BeatsSolo3,1-mickey",
      "BeatsSolo3,1-thirdman",
      "BeatsSolo3,1-line",
      "BeatsSolo3,1-newyears",
      "BeatsSolo3,1-nayva"
    ],
    "hideChildren": false
  },
  "Beats Studio³ Wireless": {
    "name": "Beats Studio³ Wireless",
    "type": "Beats Headphones",
    "order": 9,
    "devices": [
      "BeatsStudio3,2",
      "BeatsStudio3,2-acw",
      "BeatsStudio3,2-psychworld",
      "BeatsStudio3,2-faze",
      "BeatsStudio3,2-nba",
      "BeatsStudio3,2-ghetto",
      "BeatsStudio3,2-djkhaled",
      "BeatsStudio3,2-cosmophone",
      "BeatsStudio3,2-neymar",
      "BeatsStudio3,2-violet",
      "BeatsStudio3,2-connor",
      "BeatsStudio3,2-madhappy"
    ],
    "hideChildren": false
  },
  "Beats Solo Pro": {
    "name": "Beats Solo Pro",
    "type": "Beats Headphones",
    "order": 10,
    "devices": [
      "BeatsSoloPro1,1",
      "BeatsSoloPro1,1-eastside",
      "BeatsSoloPro1,1-verdy"
    ],
    "hideChildren": false
  },
  "Beats Solo": {
    "name": "Beats Solo",
    "type": "Beats Headphones",
    "devices": [
      "Beats Solo"
    ],
    "hideChildren": false,
    "order": 11
  },
  "Beats Wireless 1.5": {
    "name": "Beats Wireless 1.5",
    "type": "Beats Headphones",
    "devices": [
      "Beats Wireless 1.5"
    ],
    "hideChildren": false,
    "order": 12
  },
  "Beats Wireless": {
    "name": "Beats Wireless",
    "type": "Beats Headphones",
    "devices": [
      "Beats Wireless"
    ],
    "hideChildren": false,
    "order": 13
  },
  "Beats Pill (1st generation)": {
    "name": "Beats Pill (1st generation)",
    "type": "Beats Speakers",
    "order": 0,
    "devices": [
      "Beats Pill (1st generation)",
      "Pretty Sweet Pill",
      "Beats Pill (1st generation) Alexander Wang Edition",
      "Beats Pill (1st generation) Barry McGee Edition"
    ],
    "hideChildren": false
  },
  "Beats Pill (2nd generation)": {
    "name": "Beats Pill (2nd generation)",
    "type": "Beats Speakers",
    "order": 1,
    "devices": [
      "Beats Pill (2nd generation)",
      "Beats Pill (2nd generation) Gloss Gold Edition",
      "Beats Pill (2nd generation) MCM Edition",
      "Beats Pill (2nd generation) Barry McGee Edition",
      "Beats Pill (2nd generation) Nicki Minaj Edition",
      "Beats Pill (2nd generation) fragment design Edition",
      "Beats Pill (2nd generation) KITH Edition",
      "Beats Pill (2nd generation) ColorWare Safari Edition",
      "Beats Pill (2nd generation) Shady Records Edition"
    ],
    "hideChildren": false
  },
  "Beats Pill+": {
    "name": "Beats Pill+",
    "type": "Beats Speakers",
    "order": 2,
    "devices": [
      "Beats Pill+",
      "Beats Pill+ Stussy Edition",
      "Beats Pill+ KAR AUDIO SYSTEM Edition",
      "Beats Pill+ The Malbons Edition",
      "Beats Pill+ Quai 54 Edition",
      "Beats Pill+ KITH Edition",
      "Beats Pill+ UNDEFEATED Edition",
      "Beats Pill+ FaZe Clan Edition",
      "Beats Pill+ Madhappy Edition",
      "Beats Pill+ Field Trip Recordings Edition"
    ],
    "hideChildren": false
  },
  "HomePod": {
    "name": "HomePod",
    "type": "HomePod",
    "order": 0,
    "devices": [
      "AudioAccessory1,1",
      "AudioAccessory1,2"
    ],
    "hideChildren": false
  },
  "Mac Studio": {
    "name": "Mac Studio",
    "type": "Mac Studio",
    "devices": [
      "Mac13,1",
      "Mac13,2"
    ],
    "hideChildren": false,
    "order": 0
  },
  "Mac mini (Mid 2011)": {
    "name": "Mac mini (Mid 2011)",
    "type": "Mac mini",
    "devices": [
      "Macmini5,1",
      "Macmini5,2",
      "Macmini5,3"
    ],
    "hideChildren": false,
    "order": 0
  },
  "Mac mini (Late 2012)": {
    "name": "Mac mini (Late 2012)",
    "type": "Mac mini",
    "devices": [
      "Macmini6,1",
      "Macmini6,2"
    ],
    "hideChildren": false,
    "order": 1
  },
  "Developer Transition Kit": {
    "name": "Developer Transition Kit",
    "type": "Mac mini",
    "devices": [
      "ADP3,2"
    ],
    "hideChildren": false,
    "order": 2
  },
  "MacBook Pro (Retina, 15-inch, Late 2013)": {
    "name": "MacBook Pro (Retina, 15-inch, Late 2013)",
    "type": "MacBook Pro",
    "devices": [
      "MacBookPro11,2-Late-2013",
      "MacBookPro11,3-Late-2013"
    ],
    "hideChildren": false,
    "order": 0
  },
  "MacBook Pro (Retina, 15-inch, Mid 2014)": {
    "name": "MacBook Pro (Retina, 15-inch, Mid 2014)",
    "type": "MacBook Pro",
    "devices": [
      "MacBookPro11,2-Mid-2014",
      "MacBookPro11,3-Mid-2014"
    ],
    "hideChildren": false,
    "order": 1
  },
  "MacBook Pro (Retina, 15-inch, Mid 2015)": {
    "name": "MacBook Pro (Retina, 15-inch, Mid 2015)",
    "type": "MacBook Pro",
    "devices": [
      "MacBookPro11,4",
      "MacBookPro11,5"
    ],
    "hideChildren": false,
    "order": 2
  },
  "MacBook Pro (13-inch, 2016)": {
    "name": "MacBook Pro (13-inch, 2016)",
    "type": "MacBook Pro",
    "devices": [
      "MacBookPro13,1",
      "MacBookPro13,2"
    ],
    "hideChildren": false,
    "order": 3
  },
  "MacBook Pro (13-inch, 2017)": {
    "name": "MacBook Pro (13-inch, 2017)",
    "type": "MacBook Pro",
    "devices": [
      "MacBookPro14,1",
      "MacBookPro14,2"
    ],
    "hideChildren": false,
    "order": 4
  },
  "MacBook Pro (15-inch, 2018)": {
    "name": "MacBook Pro (15-inch, 2018)",
    "type": "MacBook Pro",
    "devices": [
      "MacBookPro15,1-2018",
      "MacBookPro15,3-2018"
    ],
    "hideChildren": false,
    "order": 5
  },
  "MacBook Pro (13-inch, 2019)": {
    "name": "MacBook Pro (13-inch, 2019)",
    "type": "MacBook Pro",
    "devices": [
      "MacBookPro15,2-2019",
      "MacBookPro15,4"
    ],
    "hideChildren": false,
    "order": 6
  },
  "MacBook Pro (15-inch, 2019)": {
    "name": "MacBook Pro (15-inch, 2019)",
    "type": "MacBook Pro",
    "devices": [
      "MacBookPro15,1-2019",
      "MacBookPro15,3-2019"
    ],
    "hideChildren": false,
    "order": 7
  },
  "MacBook Pro (16-inch, 2019)": {
    "name": "MacBook Pro (16-inch, 2019)",
    "type": "MacBook Pro",
    "devices": [
      "MacBookPro16,1",
      "MacBookPro16,4"
    ],
    "hideChildren": false,
    "order": 8
  },
  "MacBook Pro (13-inch, 2020)": {
    "name": "MacBook Pro (13-inch, 2020)",
    "type": "MacBook Pro",
    "devices": [
      "MacBookPro16,2",
      "MacBookPro16,3"
    ],
    "hideChildren": false,
    "order": 9
  },
  "MacBook Pro (14-inch, 2021)": {
    "name": "MacBook Pro (14-inch, 2021)",
    "type": "MacBook Pro",
    "devices": [
      "MacBookPro18,3",
      "MacBookPro18,4"
    ],
    "hideChildren": false,
    "order": 10
  },
  "MacBook Pro (16-inch, 2021)": {
    "name": "MacBook Pro (16-inch, 2021)",
    "type": "MacBook Pro",
    "devices": [
      "MacBookPro18,1",
      "MacBookPro18,2"
    ],
    "hideChildren": false,
    "order": 11
  },
  "iMac Pro (Retina 5K, 27-inch, Late 2017)": {
    "name": "iMac Pro (Retina 5K, 27-inch, Late 2017)",
    "type": "iMac",
    "devices": [
      "iMacPro1,1"
    ],
    "hideChildren": false,
    "order": 0
  },
  "iMac (Retina 5K, 27-inch, 2020)": {
    "name": "iMac (Retina 5K, 27-inch, 2020)",
    "type": "iMac",
    "devices": [
      "iMac20,1",
      "iMac20,2"
    ],
    "hideChildren": false,
    "order": 1
  },
  "iMac (24-inch, M1, 2021)": {
    "name": "iMac (24-inch, M1, 2021)",
    "type": "iMac",
    "devices": [
      "iMac21,1",
      "iMac21,2"
    ],
    "hideChildren": false,
    "order": 2
  },
  "iPad 2": {
    "name": "iPad 2",
    "type": "iPad",
    "order": 0,
    "devices": [
      "iPad2,1",
      "iPad2,2",
      "iPad2,3",
      "iPad2,4"
    ],
    "hideChildren": false
  },
  "iPad (3rd generation)": {
    "name": "iPad (3rd generation)",
    "type": "iPad",
    "order": 1,
    "devices": [
      "iPad3,1",
      "iPad3,2",
      "iPad3,3"
    ],
    "hideChildren": false
  },
  "iPad (4th generation)": {
    "name": "iPad (4th generation)",
    "type": "iPad",
    "order": 2,
    "devices": [
      "iPad3,4",
      "iPad3,5",
      "iPad3,6"
    ],
    "hideChildren": false
  },
  "iPad (5th generation)": {
    "name": "iPad (5th generation)",
    "type": "iPad",
    "order": 3,
    "devices": [
      "iPad6,11",
      "iPad6,12"
    ],
    "hideChildren": false
  },
  "iPad (6th generation)": {
    "name": "iPad (6th generation)",
    "type": "iPad",
    "order": 4,
    "devices": [
      "iPad7,5",
      "iPad7,6"
    ],
    "hideChildren": false
  },
  "iPad (7th generation)": {
    "name": "iPad (7th generation)",
    "type": "iPad",
    "order": 5,
    "devices": [
      "iPad7,11",
      "iPad7,12"
    ],
    "hideChildren": false
  },
  "iPad (8th generation)": {
    "name": "iPad (8th generation)",
    "type": "iPad",
    "order": 6,
    "devices": [
      "iPad11,6",
      "iPad11,7"
    ],
    "hideChildren": false
  },
  "iPad (9th generation)": {
    "name": "iPad (9th generation)",
    "type": "iPad",
    "order": 7,
    "devices": [
      "iPad12,1",
      "iPad12,2"
    ],
    "hideChildren": false
  },
  "iPad Air": {
    "name": "iPad Air",
    "type": "iPad Air",
    "order": 0,
    "devices": [
      "iPad4,1",
      "iPad4,2",
      "iPad4,3"
    ],
    "hideChildren": false
  },
  "iPad Air 2": {
    "name": "iPad Air 2",
    "type": "iPad Air",
    "order": 1,
    "devices": [
      "iPad5,3",
      "iPad5,4"
    ],
    "hideChildren": false
  },
  "iPad Air (3rd generation)": {
    "name": "iPad Air (3rd generation)",
    "type": "iPad Air",
    "order": 2,
    "devices": [
      "iPad11,3",
      "iPad11,4"
    ],
    "hideChildren": false
  },
  "iPad Air (4th generation)": {
    "name": "iPad Air (4th generation)",
    "type": "iPad Air",
    "order": 3,
    "devices": [
      "iPad13,1",
      "iPad13,2"
    ],
    "hideChildren": false
  },
  "iPad Air (5th generation)": {
    "name": "iPad Air (5th generation)",
    "type": "iPad Air",
    "order": 4,
    "devices": [
      "iPad13,16",
      "iPad13,17"
    ],
    "hideChildren": false
  },
  "iPad Pro (12.9-inch) (1st generation)": {
    "name": "iPad Pro (12.9-inch) (1st generation)",
    "type": "iPad Pro",
    "order": 0,
    "devices": [
      "iPad6,7",
      "iPad6,8"
    ],
    "hideChildren": false
  },
  "iPad Pro (9.7-inch)": {
    "name": "iPad Pro (9.7-inch)",
    "type": "iPad Pro",
    "order": 1,
    "devices": [
      "iPad6,3",
      "iPad6,4"
    ],
    "hideChildren": false
  },
  "iPad Pro (10.5-inch)": {
    "name": "iPad Pro (10.5-inch)",
    "type": "iPad Pro",
    "order": 2,
    "devices": [
      "iPad7,3",
      "iPad7,4"
    ],
    "hideChildren": false
  },
  "iPad Pro (12.9-inch) (2nd generation)": {
    "name": "iPad Pro (12.9-inch) (2nd generation)",
    "type": "iPad Pro",
    "order": 3,
    "devices": [
      "iPad7,1",
      "iPad7,2"
    ],
    "hideChildren": false
  },
  "iPad Pro 11-inch (1st generation)": {
    "name": "iPad Pro 11-inch (1st generation)",
    "type": "iPad Pro",
    "order": 4,
    "devices": [
      "iPad8,1",
      "iPad8,2",
      "iPad8,3",
      "iPad8,4"
    ],
    "hideChildren": false
  },
  "iPad Pro 12.9-inch (3rd generation)": {
    "name": "iPad Pro 12.9-inch (3rd generation)",
    "type": "iPad Pro",
    "order": 5,
    "devices": [
      "iPad8,5",
      "iPad8,6",
      "iPad8,7",
      "iPad8,8"
    ],
    "hideChildren": false
  },
  "iPad Pro 11-inch (2nd generation)": {
    "name": "iPad Pro 11-inch (2nd generation)",
    "type": "iPad Pro",
    "order": 6,
    "devices": [
      "iPad8,9",
      "iPad8,10"
    ],
    "hideChildren": false
  },
  "iPad Pro 12.9-inch (4th generation)": {
    "name": "iPad Pro 12.9-inch (4th generation)",
    "type": "iPad Pro",
    "order": 7,
    "devices": [
      "iPad8,11",
      "iPad8,12"
    ],
    "hideChildren": false
  },
  "iPad Pro 11-inch (3rd generation)": {
    "name": "iPad Pro 11-inch (3rd generation)",
    "type": "iPad Pro",
    "order": 8,
    "devices": [
      "iPad13,4",
      "iPad13,5",
      "iPad13,6",
      "iPad13,7"
    ],
    "hideChildren": false
  },
  "iPad Pro 12.9-inch (5th generation)": {
    "name": "iPad Pro 12.9-inch (5th generation)",
    "type": "iPad Pro",
    "order": 9,
    "devices": [
      "iPad13,8",
      "iPad13,9",
      "iPad13,10",
      "iPad13,11"
    ],
    "hideChildren": false
  },
  "iPad mini": {
    "name": "iPad mini",
    "type": "iPad mini",
    "order": 0,
    "devices": [
      "iPad2,5",
      "iPad2,6",
      "iPad2,7"
    ],
    "hideChildren": false
  },
  "iPad mini 2": {
    "name": "iPad mini 2",
    "type": "iPad mini",
    "order": 1,
    "devices": [
      "iPad4,4",
      "iPad4,5",
      "iPad4,6"
    ],
    "hideChildren": false
  },
  "iPad mini 3": {
    "name": "iPad mini 3",
    "type": "iPad mini",
    "order": 2,
    "devices": [
      "iPad4,7",
      "iPad4,8",
      "iPad4,9"
    ],
    "hideChildren": false
  },
  "iPad mini 4": {
    "name": "iPad mini 4",
    "type": "iPad mini",
    "order": 3,
    "devices": [
      "iPad5,1",
      "iPad5,2"
    ],
    "hideChildren": false
  },
  "iPad mini (5th generation)": {
    "name": "iPad mini (5th generation)",
    "type": "iPad mini",
    "order": 4,
    "devices": [
      "iPad11,1",
      "iPad11,2"
    ],
    "hideChildren": false
  },
  "iPad mini (6th generation)": {
    "name": "iPad mini (6th generation)",
    "type": "iPad mini",
    "order": 5,
    "devices": [
      "iPad14,1",
      "iPad14,2"
    ],
    "hideChildren": false
  },
  "iPhone 2G": {
    "name": "iPhone 2G",
    "type": "iPhone",
    "order": 0,
    "devices": [
      "iPhone1,1"
    ],
    "hideChildren": false
  },
  "iPhone 4": {
    "name": "iPhone 4",
    "type": "iPhone",
    "order": 1,
    "devices": [
      "iPhone3,1",
      "iPhone3,2",
      "iPhone3,3"
    ],
    "hideChildren": false
  },
  "iPhone 5": {
    "name": "iPhone 5",
    "type": "iPhone",
    "order": 2,
    "devices": [
      "iPhone5,1",
      "iPhone5,2"
    ],
    "hideChildren": false
  },
  "iPhone 5c": {
    "name": "iPhone 5c",
    "type": "iPhone",
    "order": 3,
    "devices": [
      "iPhone5,3",
      "iPhone5,4"
    ],
    "hideChildren": false
  },
  "iPhone 5s": {
    "name": "iPhone 5s",
    "type": "iPhone",
    "order": 4,
    "devices": [
      "iPhone6,1",
      "iPhone6,2"
    ],
    "hideChildren": false
  },
  "iPhone 6": {
    "name": "iPhone 6",
    "type": "iPhone",
    "order": 5,
    "devices": [
      "iPhone7,1",
      "iPhone7,2"
    ],
    "subgroups": [
      {
        "name": "iPhone 6",
        "type": "iPhone",
        "order": 0,
        "devices": [
          "iPhone7,2"
        ]
      },
      {
        "name": "iPhone 6 Plus",
        "type": "iPhone",
        "order": 1,
        "devices": [
          "iPhone7,2"
        ]
      }
    ],
    "hideChildren": false
  },
  "iPhone 6s": {
    "name": "iPhone 6s",
    "type": "iPhone",
    "order": 6,
    "devices": [
      "iPhone8,1",
      "iPhone8,2"
    ],
    "subgroups": [
      {
        "name": "iPhone 6s",
        "type": "iPhone",
        "order": 0,
        "devices": [
          "iPhone8,1"
        ]
      },
      {
        "name": "iPhone 6s Plus",
        "type": "iPhone",
        "order": 1,
        "devices": [
          "iPhone8,2"
        ]
      }
    ],
    "hideChildren": false
  },
  "iPhone 7": {
    "name": "iPhone 7",
    "type": "iPhone",
    "order": 7,
    "devices": [
      "iPhone9,1",
      "iPhone9,2",
      "iPhone9,3",
      "iPhone9,4"
    ],
    "subgroups": [
      {
        "name": "iPhone 7",
        "type": "iPhone",
        "order": 0,
        "devices": [
          "iPhone9,1",
          "iPhone9,3"
        ]
      },
      {
        "name": "iPhone 7 Plus",
        "type": "iPhone",
        "order": 1,
        "devices": [
          "iPhone9,2",
          "iPhone9,4"
        ]
      }
    ],
    "hideChildren": false
  },
  "iPhone 8": {
    "name": "iPhone 8",
    "type": "iPhone",
    "order": 8,
    "devices": [
      "iPhone10,1",
      "iPhone10,2",
      "iPhone10,4",
      "iPhone10,5"
    ],
    "subgroups": [
      {
        "name": "iPhone 8",
        "type": "iPhone",
        "order": 0,
        "devices": [
          "iPhone10,1",
          "iPhone10,4"
        ]
      },
      {
        "name": "iPhone 8 Plus",
        "type": "iPhone",
        "order": 1,
        "devices": [
          "iPhone10,2",
          "iPhone10,5"
        ]
      }
    ],
    "hideChildren": false
  },
  "iPhone X": {
    "name": "iPhone X",
    "type": "iPhone",
    "order": 9,
    "devices": [
      "iPhone10,3",
      "iPhone10,6"
    ],
    "hideChildren": false
  },
  "iPhone XS": {
    "name": "iPhone XS",
    "type": "iPhone",
    "order": 10,
    "devices": [
      "iPhone11,2",
      "iPhone11,4",
      "iPhone11,6"
    ],
    "subgroups": [
      {
        "name": "iPhone XS",
        "type": "iPhone",
        "order": 0,
        "devices": [
          "iPhone11,2"
        ]
      },
      {
        "name": "iPhone XS Max",
        "type": "iPhone",
        "order": 1,
        "devices": [
          "iPhone11,4",
          "iPhone11,6"
        ]
      }
    ],
    "hideChildren": false
  },
  "iPhone 11 Pro": {
    "name": "iPhone 11 Pro",
    "type": "iPhone",
    "order": 11,
    "devices": [
      "iPhone12,3",
      "iPhone12,5"
    ],
    "subgroups": [
      {
        "name": "iPhone 11 Pro",
        "type": "iPhone",
        "order": 0,
        "devices": [
          "iPhone12,3"
        ]
      },
      {
        "name": "iPhone 11 Pro Max",
        "type": "iPhone",
        "order": 1,
        "devices": [
          "iPhone12,5"
        ]
      }
    ],
    "hideChildren": false
  },
  "iPhone 12 Pro": {
    "name": "iPhone 12 Pro",
    "type": "iPhone",
    "order": 12,
    "devices": [
      "iPhone13,3",
      "iPhone13,4"
    ],
    "subgroups": [
      {
        "name": "iPhone 12 Pro",
        "type": "iPhone",
        "order": 0,
        "devices": [
          "iPhone13,3"
        ]
      },
      {
        "name": "iPhone 12 Pro Max",
        "type": "iPhone",
        "order": 1,
        "devices": [
          "iPhone13,4"
        ]
      }
    ],
    "hideChildren": false
  },
  "iPhone 12": {
    "name": "iPhone 12",
    "type": "iPhone",
    "order": 13,
    "devices": [
      "iPhone13,1",
      "iPhone13,2"
    ],
    "subgroups": [
      {
        "name": "iPhone 12",
        "type": "iPhone",
        "order": 0,
        "devices": [
          "iPhone13,2"
        ]
      },
      {
        "name": "iPhone 12 mini",
        "type": "iPhone",
        "order": 1,
        "devices": [
          "iPhone13,1"
        ]
      }
    ],
    "hideChildren": false
  },
  "iPhone 13 Pro": {
    "name": "iPhone 13 Pro",
    "type": "iPhone",
    "order": 14,
    "devices": [
      "iPhone14,2",
      "iPhone14,3"
    ],
    "subgroups": [
      {
        "name": "iPhone 13 Pro",
        "type": "iPhone",
        "order": 0,
        "devices": [
          "iPhone14,2"
        ]
      },
      {
        "name": "iPhone 13 Pro Max",
        "type": "iPhone",
        "order": 1,
        "devices": [
          "iPhone14,3"
        ]
      }
    ],
    "hideChildren": false
  },
  "iPhone 13": {
    "name": "iPhone 13",
    "type": "iPhone",
    "order": 15,
    "devices": [
      "iPhone14,4",
      "iPhone14,5"
    ],
    "subgroups": [
      {
        "name": "iPhone 13",
        "type": "iPhone",
        "order": 0,
        "devices": [
          "iPhone14,5"
        ]
      },
      {
        "name": "iPhone 13 mini",
        "type": "iPhone",
        "order": 1,
        "devices": [
          "iPhone14,4"
        ]
      }
    ],
    "hideChildren": false
  },
  "iPod with color display": {
    "name": "iPod with color display",
    "type": "iPod",
    "devices": [
      "iPod photo",
      "iPod with color display"
    ],
    "hideChildren": false,
    "order": 0
  },
  "iPod (5th generation)": {
    "name": "iPod (5th generation)",
    "type": "iPod",
    "devices": [
      "iPod (5th generation)",
      "iPod (5th generation Late 2006)"
    ],
    "hideChildren": false,
    "order": 1
  },
  "iPod classic": {
    "name": "iPod classic",
    "type": "iPod",
    "devices": [
      "iPod classic",
      "iPod classic (120 GB)",
      "iPod classic 160 GB (Late 2009)"
    ],
    "hideChildren": false,
    "order": 2
  },
  "iPod nano (7th generation)": {
    "name": "iPod nano (7th generation)",
    "type": "iPod nano",
    "devices": [
      "iPod nano (7th generation)",
      "iPod nano (7th generation Mid 2015)"
    ],
    "hideChildren": false,
    "order": 0
  },
  "iPod shuffle (3rd generation)": {
    "name": "iPod shuffle (3rd generation)",
    "type": "iPod shuffle",
    "devices": [
      "iPod shuffle (3rd generation)",
      "iPod shuffle (3rd generation Late 2009)"
    ],
    "hideChildren": false,
    "order": 0
  },
  "iPod shuffle (4th generation)": {
    "name": "iPod shuffle (4th generation)",
    "type": "iPod shuffle",
    "devices": [
      "iPod shuffle (4th generation)",
      "iPod shuffle (4th generation Late 2012)",
      "iPod shuffle (4th generation Mid 2015)"
    ],
    "hideChildren": false,
    "order": 1
  },
  "Lightning to SD Card Camera Reader (USB)": {
    "name": "Lightning to SD Card Camera Reader (USB)",
    "type": "Adapters",
    "devices": [
      "Lightning to SD Card Camera Reader (USB)"
    ],
    "order": 0
  },
  "MagSafe Airline Adapter": {
    "name": "MagSafe Airline Adapter",
    "type": "Adapters",
    "devices": [
      "MagSafe Airline Adapter"
    ],
    "order": 1
  },
  "AirPods (1st generation)": {
    "name": "AirPods (1st generation)",
    "type": "AirPods",
    "devices": [
      "AirPods1,1"
    ],
    "order": 0
  },
  "Apple Pencil (1st generation)": {
    "name": "Apple Pencil (1st generation)",
    "type": "Apple Pencil",
    "devices": [
      "Apple Pencil (1st generation)"
    ],
    "order": 0
  },
  "Apple Pencil (2nd generation)": {
    "name": "Apple Pencil (2nd generation)",
    "type": "Apple Pencil",
    "devices": [
      "Apple Pencil (2nd generation)"
    ],
    "order": 1
  },
  "Apple Cinema Display (20-inch, 2003)": {
    "name": "Apple Cinema Display (20-inch, 2003)",
    "type": "Display",
    "devices": [
      "Apple Cinema Display (20-inch, 2003)"
    ],
    "order": 0
  },
  "Apple Cinema Display (20-inch, 2004)": {
    "name": "Apple Cinema Display (20-inch, 2004)",
    "type": "Display",
    "devices": [
      "Apple Cinema Display (20-inch, 2004)"
    ],
    "order": 1
  },
  "Apple Cinema Display (20-inch, 2006)": {
    "name": "Apple Cinema Display (20-inch, 2006)",
    "type": "Display",
    "devices": [
      "Apple Cinema Display (20-inch, 2006)"
    ],
    "order": 2
  },
  "Apple Cinema Display (22-inch, ADC)": {
    "name": "Apple Cinema Display (22-inch, ADC)",
    "type": "Display",
    "devices": [
      "Apple Cinema Display (22-inch, ADC)"
    ],
    "order": 3
  },
  "Apple Cinema Display (22-inch, DVI-D)": {
    "name": "Apple Cinema Display (22-inch, DVI-D)",
    "type": "Display",
    "devices": [
      "Apple Cinema Display (22-inch, DVI-D)"
    ],
    "order": 4
  },
  "Apple Cinema HD Display (2002)": {
    "name": "Apple Cinema HD Display (2002)",
    "type": "Display",
    "devices": [
      "Apple Cinema HD Display (2002)"
    ],
    "order": 5
  },
  "Apple Cinema HD Display (23-inch, 2004)": {
    "name": "Apple Cinema HD Display (23-inch, 2004)",
    "type": "Display",
    "devices": [
      "Apple Cinema HD Display (23-inch, 2004)"
    ],
    "order": 7
  },
  "Apple Cinema HD Display (30-inch, 2004)": {
    "name": "Apple Cinema HD Display (30-inch, 2004)",
    "type": "Display",
    "devices": [
      "Apple Cinema HD Display (30-inch, 2004)"
    ],
    "order": 9
  },
  "Apple Thunderbolt Display": {
    "name": "Apple Thunderbolt Display",
    "type": "Display",
    "devices": [
      "Apple Thunderbolt Display"
    ],
    "order": 10
  },
  "Studio Display": {
    "name": "Studio Display",
    "type": "Display",
    "devices": [
      "AppleDisplay2,1"
    ],
    "order": 11
  },
  "LED Cinema Display (24-inch)": {
    "name": "LED Cinema Display (24-inch)",
    "type": "Display",
    "devices": [
      "LED Cinema Display (24-inch)"
    ],
    "order": 12
  },
  "LED Cinema Display (27-inch)": {
    "name": "LED Cinema Display (27-inch)",
    "type": "Display",
    "devices": [
      "LED Cinema Display (27-inch)"
    ],
    "order": 13
  },
  "Apple TV (1st generation)": {
    "name": "Apple TV (1st generation)",
    "type": "Apple TV",
    "devices": [
      "AppleTV1,1"
    ],
    "order": 0
  },
  "Apple TV 4K (2nd generation)": {
    "name": "Apple TV 4K (2nd generation)",
    "type": "Apple TV",
    "devices": [
      "AppleTV11,1"
    ],
    "order": 1
  },
  "Apple TV (2nd generation)": {
    "name": "Apple TV (2nd generation)",
    "type": "Apple TV",
    "devices": [
      "AppleTV2,1"
    ],
    "order": 2
  },
  "Apple TV HD (4th generation)": {
    "name": "Apple TV HD (4th generation)",
    "type": "Apple TV",
    "devices": [
      "AppleTV5,3"
    ],
    "order": 3
  },
  "Apple TV 4K (1st generation)": {
    "name": "Apple TV 4K (1st generation)",
    "type": "Apple TV",
    "devices": [
      "AppleTV6,2"
    ],
    "order": 4
  },
  "iPhone Bluetooth Headset": {
    "name": "iPhone Bluetooth Headset",
    "type": "Audio",
    "devices": [
      "iPhone Bluetooth Headset"
    ],
    "order": 0
  },
  "iPod Hi-Fi": {
    "name": "iPod Hi-Fi",
    "type": "Audio",
    "devices": [
      "iPod Hi-Fi"
    ],
    "order": 1
  },
  "HomePod mini": {
    "name": "HomePod mini",
    "type": "HomePod",
    "devices": [
      "AudioAccessory5,1"
    ],
    "order": 0
  },
  "Beats Fit Pro": {
    "name": "Beats Fit Pro",
    "type": "Beats Earbuds",
    "devices": [
      "Beats Fit Pro"
    ],
    "order": 0
  },
  "Beats Tour (1st generation)": {
    "name": "Beats Tour (1st generation)",
    "type": "Beats Earbuds",
    "devices": [
      "Beats Tour (1st generation)"
    ],
    "order": 1
  },
  "Diddybeats": {
    "name": "Diddybeats",
    "type": "Beats Earbuds",
    "devices": [
      "Diddybeats"
    ],
    "order": 2
  },
  "Heartbeats (1st generation)": {
    "name": "Heartbeats (1st generation)",
    "type": "Beats Earbuds",
    "devices": [
      "Heartbeats (1st generation)"
    ],
    "order": 3
  },
  "Heartbeats (2nd generation)": {
    "name": "Heartbeats (2nd generation)",
    "type": "Beats Earbuds",
    "devices": [
      "Heartbeats (2nd generation)"
    ],
    "order": 4
  },
  "Powerbeats²": {
    "name": "Powerbeats²",
    "type": "Beats Earbuds",
    "devices": [
      "Powerbeats2"
    ],
    "order": 5
  },
  "urBeats²": {
    "name": "urBeats²",
    "type": "Beats Earbuds",
    "devices": [
      "urBeats2"
    ],
    "order": 6
  },
  "urBeats³": {
    "name": "urBeats³",
    "type": "Beats Earbuds",
    "devices": [
      "urBeats3"
    ],
    "order": 7
  },
  "Beats EP": {
    "name": "Beats EP",
    "type": "Beats Headphones",
    "devices": [
      "Beats EP"
    ],
    "order": 0
  },
  "Beats Mixr": {
    "name": "Beats Mixr",
    "type": "Beats Headphones",
    "devices": [
      "Beats Mixr"
    ],
    "order": 1
  },
  "Beatbox Portable (1st generation)": {
    "name": "Beatbox Portable (1st generation)",
    "type": "Beats Speakers",
    "devices": [
      "Beatbox Portable (1st generation)"
    ],
    "order": 0
  },
  "Beatbox Portable (2nd generation)": {
    "name": "Beatbox Portable (2nd generation)",
    "type": "Beats Speakers",
    "devices": [
      "Beatbox Portable (2nd generation)"
    ],
    "order": 1
  },
  "Beatbox Portable (3rd generation)": {
    "name": "Beatbox Portable (3rd generation)",
    "type": "Beats Speakers",
    "devices": [
      "Beatbox Portable (3rd generation)"
    ],
    "order": 2
  },
  "Beatbox": {
    "name": "Beatbox",
    "type": "Beats Speakers",
    "devices": [
      "Beatbox"
    ],
    "order": 3
  },
  "Beats Pill SE": {
    "name": "Beats Pill SE",
    "type": "Beats Speakers",
    "devices": [
      "Beats Pill SE"
    ],
    "order": 4
  },
  "Beats Pill XL": {
    "name": "Beats Pill XL",
    "type": "Beats Speakers",
    "devices": [
      "Beats Pill XL"
    ],
    "order": 5
  },
  "Beddit 3 Sleep Monitor": {
    "name": "Beddit 3 Sleep Monitor",
    "type": "Beddit",
    "devices": [
      "Beddit 3 Sleep Monitor"
    ],
    "order": 0
  },
  "Beddit 3.5 Sleep Monitor": {
    "name": "Beddit 3.5 Sleep Monitor",
    "type": "Beddit",
    "devices": [
      "Beddit 3.5 Sleep Monitor"
    ],
    "order": 1
  },
  "Apple Keyboard (1st generation)": {
    "name": "Apple Keyboard (1st generation)",
    "type": "Keyboard",
    "devices": [
      "Apple Keyboard (1st generation)"
    ],
    "order": 0
  },
  "Apple Keyboard (2nd generation)": {
    "name": "Apple Keyboard (2nd generation)",
    "type": "Keyboard",
    "devices": [
      "Apple Keyboard (2nd generation)"
    ],
    "order": 1
  },
  "Apple Keyboard (3rd generation)": {
    "name": "Apple Keyboard (3rd generation)",
    "type": "Keyboard",
    "devices": [
      "Apple Keyboard (3rd generation)"
    ],
    "order": 2
  },
  "Apple Keyboard (4th generation)": {
    "name": "Apple Keyboard (4th generation)",
    "type": "Keyboard",
    "devices": [
      "Apple Keyboard (4th generation)"
    ],
    "order": 3
  },
  "Apple Keyboard (5th generation)": {
    "name": "Apple Keyboard (5th generation)",
    "type": "Keyboard",
    "devices": [
      "Apple Keyboard (5th generation)"
    ],
    "order": 4
  },
  "Apple Wireless Keyboard (1st generation)": {
    "name": "Apple Wireless Keyboard (1st generation)",
    "type": "Keyboard",
    "devices": [
      "Apple Wireless Keyboard (1st generation)"
    ],
    "order": 5
  },
  "Apple Wireless Keyboard (2nd generation)": {
    "name": "Apple Wireless Keyboard (2nd generation)",
    "type": "Keyboard",
    "devices": [
      "Apple Wireless Keyboard (2nd generation)"
    ],
    "order": 6
  },
  "Apple Wireless Keyboard (3rd generation)": {
    "name": "Apple Wireless Keyboard (3rd generation)",
    "type": "Keyboard",
    "devices": [
      "Apple Wireless Keyboard (3rd generation)"
    ],
    "order": 7
  },
  "Apple Wireless Keyboard (4th generation)": {
    "name": "Apple Wireless Keyboard (4th generation)",
    "type": "Keyboard",
    "devices": [
      "Apple Wireless Keyboard (4th generation)"
    ],
    "order": 8
  },
  "Magic Keyboard (11-inch)": {
    "name": "Magic Keyboard (11-inch)",
    "type": "Keyboard",
    "devices": [
      "Magic Keyboard (11-inch)"
    ],
    "order": 9
  },
  "Magic Keyboard (1st generation)": {
    "name": "Magic Keyboard (1st generation)",
    "type": "Keyboard",
    "devices": [
      "Magic Keyboard (1st generation)"
    ],
    "order": 10
  },
  "Magic Keyboard (2nd generation)": {
    "name": "Magic Keyboard (2nd generation)",
    "type": "Keyboard",
    "devices": [
      "Magic Keyboard (2nd generation)"
    ],
    "order": 11
  },
  "Magic Keyboard for iPad Pro 12.9-inch (4th generation)": {
    "name": "Magic Keyboard for iPad Pro 12.9-inch (4th generation)",
    "type": "Keyboard",
    "devices": [
      "Magic Keyboard for iPad Pro 12.9-inch (4th generation)"
    ],
    "order": 12
  },
  "Magic Keyboard for iPad Pro 12.9-inch (5th generation)": {
    "name": "Magic Keyboard for iPad Pro 12.9-inch (5th generation)",
    "type": "Keyboard",
    "devices": [
      "Magic Keyboard for iPad Pro 12.9-inch (5th generation)"
    ],
    "order": 13
  },
  "Magic Keyboard with Numeric Keypad": {
    "name": "Magic Keyboard with Numeric Keypad",
    "type": "Keyboard",
    "devices": [
      "Magic Keyboard with Numeric Keypad"
    ],
    "order": 14
  },
  "Magic Keyboard with Touch ID and Numeric Keypad": {
    "name": "Magic Keyboard with Touch ID and Numeric Keypad",
    "type": "Keyboard",
    "devices": [
      "Magic Keyboard with Touch ID and Numeric Keypad"
    ],
    "order": 15
  },
  "Magic Keyboard with Touch ID": {
    "name": "Magic Keyboard with Touch ID",
    "type": "Keyboard",
    "devices": [
      "Magic Keyboard with Touch ID"
    ],
    "order": 16
  },
  "Smart Keyboard (10.5/10.2-inch)": {
    "name": "Smart Keyboard (10.5/10.2-inch)",
    "type": "Keyboard",
    "devices": [
      "Smart Keyboard (10.5-10.2-inch)"
    ],
    "order": 17
  },
  "Smart Keyboard (12.9-inch)": {
    "name": "Smart Keyboard (12.9-inch)",
    "type": "Keyboard",
    "devices": [
      "Smart Keyboard (12.9-inch)"
    ],
    "order": 18
  },
  "Smart Keyboard (9.7-inch)": {
    "name": "Smart Keyboard (9.7-inch)",
    "type": "Keyboard",
    "devices": [
      "Smart Keyboard (9.7-inch)"
    ],
    "order": 19
  },
  "Smart Keyboard Folio (11-inch)": {
    "name": "Smart Keyboard Folio (11-inch)",
    "type": "Keyboard",
    "devices": [
      "Smart Keyboard Folio (11-inch)"
    ],
    "order": 20
  },
  "Smart Keyboard Folio (12.9-inch)": {
    "name": "Smart Keyboard Folio (12.9-inch)",
    "type": "Keyboard",
    "devices": [
      "Smart Keyboard Folio (12.9-inch)"
    ],
    "order": 21
  },
  "iPad Keyboard Dock": {
    "name": "iPad Keyboard Dock",
    "type": "Keyboard",
    "devices": [
      "iPad Keyboard Dock"
    ],
    "order": 22
  },
  "MacBook Air (M2, 2022)": {
    "name": "MacBook Air (M2, 2022)",
    "type": "MacBook Air",
    "devices": [
      "Mac14,2"
    ],
    "order": 0
  },
  "MacBook Pro (13-inch, M2, 2022)": {
    "name": "MacBook Pro (13-inch, M2, 2022)",
    "type": "MacBook Pro",
    "devices": [
      "Mac14,7"
    ],
    "order": 0
  },
  "Mac Pro (Mid 2006)": {
    "name": "Mac Pro (Mid 2006)",
    "type": "Mac Pro",
    "devices": [
      "MacPro1,1"
    ],
    "order": 0
  },
  "Mac Pro (Early 2007)": {
    "name": "Mac Pro (Early 2007)",
    "type": "Mac Pro",
    "devices": [
      "MacPro2,1"
    ],
    "order": 1
  },
  "Mac Pro (Early 2008)": {
    "name": "Mac Pro (Early 2008)",
    "type": "Mac Pro",
    "devices": [
      "MacPro3,1"
    ],
    "order": 2
  },
  "Mac Pro (Early 2009)": {
    "name": "Mac Pro (Early 2009)",
    "type": "Mac Pro",
    "devices": [
      "MacPro4,1"
    ],
    "order": 3
  },
  "Mac Pro (Late 2010)": {
    "name": "Mac Pro (Late 2010)",
    "type": "Mac Pro",
    "devices": [
      "MacPro5,1-2010"
    ],
    "order": 4
  },
  "Mac Pro (Mid 2012)": {
    "name": "Mac Pro (Mid 2012)",
    "type": "Mac Pro",
    "devices": [
      "MacPro5,1-2012"
    ],
    "order": 5
  },
  "Mac Pro Server (Mid 2010)": {
    "name": "Mac Pro Server (Mid 2010)",
    "type": "Mac Pro",
    "devices": [
      "MacPro5,1-Server-2010"
    ],
    "order": 6
  },
  "Mac Pro Server (Mid 2012)": {
    "name": "Mac Pro Server (Mid 2012)",
    "type": "Mac Pro",
    "devices": [
      "MacPro5,1-Server-2012"
    ],
    "order": 7
  },
  "Mac Pro (Late 2013)": {
    "name": "Mac Pro (Late 2013)",
    "type": "Mac Pro",
    "devices": [
      "MacPro6,1"
    ],
    "order": 8
  },
  "Mac Pro (Rack, 2019)": {
    "name": "Mac Pro (Rack, 2019)",
    "type": "Mac Pro",
    "devices": [
      "MacPro7,1-Rack"
    ],
    "order": 9
  },
  "Mac Pro (2019)": {
    "name": "Mac Pro (2019)",
    "type": "Mac Pro",
    "devices": [
      "MacPro7,1"
    ],
    "order": 10
  },
  "MacBook (13-inch, Mid 2006)": {
    "name": "MacBook (13-inch, Mid 2006)",
    "type": "MacBook",
    "devices": [
      "MacBook1,1"
    ],
    "order": 0
  },
  "MacBook (Retina, 12-inch, 2017)": {
    "name": "MacBook (Retina, 12-inch, 2017)",
    "type": "MacBook",
    "devices": [
      "MacBook10,1"
    ],
    "order": 1
  },
  "MacBook (13-inch, Late 2006)": {
    "name": "MacBook (13-inch, Late 2006)",
    "type": "MacBook",
    "devices": [
      "MacBook2,1-2006"
    ],
    "order": 2
  },
  "MacBook (13-inch, Mid 2007)": {
    "name": "MacBook (13-inch, Mid 2007)",
    "type": "MacBook",
    "devices": [
      "MacBook2,1-2007"
    ],
    "order": 3
  },
  "MacBook (13-inch, Late 2007)": {
    "name": "MacBook (13-inch, Late 2007)",
    "type": "MacBook",
    "devices": [
      "MacBook3,1"
    ],
    "order": 4
  },
  "MacBook (13-inch, Early 2008)": {
    "name": "MacBook (13-inch, Early 2008)",
    "type": "MacBook",
    "devices": [
      "MacBook4,1"
    ],
    "order": 5
  },
  "MacBook (13-inch, Late 2008)": {
    "name": "MacBook (13-inch, Late 2008)",
    "type": "MacBook",
    "devices": [
      "MacBook5,1"
    ],
    "order": 6
  },
  "MacBook (13-inch, Early 2009)": {
    "name": "MacBook (13-inch, Early 2009)",
    "type": "MacBook",
    "devices": [
      "MacBook5,2-Early-2009"
    ],
    "order": 7
  },
  "MacBook (13-inch, Mid 2009)": {
    "name": "MacBook (13-inch, Mid 2009)",
    "type": "MacBook",
    "devices": [
      "MacBook5,2-Mid-2009"
    ],
    "order": 8
  },
  "MacBook (13-inch, Late 2009)": {
    "name": "MacBook (13-inch, Late 2009)",
    "type": "MacBook",
    "devices": [
      "MacBook6,1"
    ],
    "order": 9
  },
  "MacBook (13-inch, Mid 2010)": {
    "name": "MacBook (13-inch, Mid 2010)",
    "type": "MacBook",
    "devices": [
      "MacBook7,1"
    ],
    "order": 10
  },
  "MacBook (Retina, 12-inch, Early 2015)": {
    "name": "MacBook (Retina, 12-inch, Early 2015)",
    "type": "MacBook",
    "devices": [
      "MacBook8,1"
    ],
    "order": 11
  },
  "MacBook (Retina, 12-inch, Early 2016)": {
    "name": "MacBook (Retina, 12-inch, Early 2016)",
    "type": "MacBook",
    "devices": [
      "MacBook9,1"
    ],
    "order": 12
  },
  "MacBook Air (Early 2008)": {
    "name": "MacBook Air (Early 2008)",
    "type": "MacBook Air",
    "devices": [
      "MacBookAir1,1"
    ],
    "order": 0
  },
  "MacBook Air (M1, Late 2020)": {
    "name": "MacBook Air (M1, Late 2020)",
    "type": "MacBook Air",
    "devices": [
      "MacBookAir10,1"
    ],
    "order": 1
  },
  "MacBook Air (Late 2008)": {
    "name": "MacBook Air (Late 2008)",
    "type": "MacBook Air",
    "devices": [
      "MacBookAir2,1-2008"
    ],
    "order": 2
  },
  "MacBook Air (Mid 2009)": {
    "name": "MacBook Air (Mid 2009)",
    "type": "MacBook Air",
    "devices": [
      "MacBookAir2,1-2009"
    ],
    "order": 3
  },
  "MacBook Air (11-inch, Late 2010)": {
    "name": "MacBook Air (11-inch, Late 2010)",
    "type": "MacBook Air",
    "devices": [
      "MacBookAir3,1"
    ],
    "order": 4
  },
  "MacBook Air (13-inch, Late 2010)": {
    "name": "MacBook Air (13-inch, Late 2010)",
    "type": "MacBook Air",
    "devices": [
      "MacBookAir3,2"
    ],
    "order": 5
  },
  "MacBook Air (11-inch, Mid 2011)": {
    "name": "MacBook Air (11-inch, Mid 2011)",
    "type": "MacBook Air",
    "devices": [
      "MacBookAir5,1"
    ],
    "order": 6
  },
  "MacBook Air (13-inch, Mid 2011)": {
    "name": "MacBook Air (13-inch, Mid 2011)",
    "type": "MacBook Air",
    "devices": [
      "MacBookAir4,2"
    ],
    "order": 7
  },
  "MacBook Air (11-inch, Mid 2012)": {
    "name": "MacBook Air (11-inch, Mid 2012)",
    "type": "MacBook Air",
    "devices": [
      "MacBookAir4,1"
    ],
    "order": 8
  },
  "MacBook Air (13-inch, Mid 2012)": {
    "name": "MacBook Air (13-inch, Mid 2012)",
    "type": "MacBook Air",
    "devices": [
      "MacBookAir5,2"
    ],
    "order": 9
  },
  "MacBook Air (11-inch, Mid 2013)": {
    "name": "MacBook Air (11-inch, Mid 2013)",
    "type": "MacBook Air",
    "devices": [
      "MacBookAir6,1-2013"
    ],
    "order": 10
  },
  "MacBook Air (11-inch, Early 2014)": {
    "name": "MacBook Air (11-inch, Early 2014)",
    "type": "MacBook Air",
    "devices": [
      "MacBookAir6,1-2014"
    ],
    "order": 11
  },
  "MacBook Air (13-inch, Mid 2013)": {
    "name": "MacBook Air (13-inch, Mid 2013)",
    "type": "MacBook Air",
    "devices": [
      "MacBookAir6,2-2013"
    ],
    "order": 12
  },
  "MacBook Air (13-inch, Early 2014)": {
    "name": "MacBook Air (13-inch, Early 2014)",
    "type": "MacBook Air",
    "devices": [
      "MacBookAir6,2-2014"
    ],
    "order": 13
  },
  "MacBook Air (11-inch, Early 2015)": {
    "name": "MacBook Air (11-inch, Early 2015)",
    "type": "MacBook Air",
    "devices": [
      "MacBookAir7,1"
    ],
    "order": 14
  },
  "MacBook Air (13-inch, Early 2015)": {
    "name": "MacBook Air (13-inch, Early 2015)",
    "type": "MacBook Air",
    "devices": [
      "MacBookAir7,2-2015"
    ],
    "order": 15
  },
  "MacBook Air (13-inch, 2017)": {
    "name": "MacBook Air (13-inch, 2017)",
    "type": "MacBook Air",
    "devices": [
      "MacBookAir7,2-2017"
    ],
    "order": 16
  },
  "MacBook Air (Retina, 13-inch, 2018)": {
    "name": "MacBook Air (Retina, 13-inch, 2018)",
    "type": "MacBook Air",
    "devices": [
      "MacBookAir8,1"
    ],
    "order": 17
  },
  "MacBook Air (Retina, 13-inch, 2019)": {
    "name": "MacBook Air (Retina, 13-inch, 2019)",
    "type": "MacBook Air",
    "devices": [
      "MacBookAir8,2"
    ],
    "order": 18
  },
  "MacBook Air (Retina, 13-inch, 2020)": {
    "name": "MacBook Air (Retina, 13-inch, 2020)",
    "type": "MacBook Air",
    "devices": [
      "MacBookAir9,1"
    ],
    "order": 19
  },
  "MacBook Pro (15-inch, Early 2006)": {
    "name": "MacBook Pro (15-inch, Early 2006)",
    "type": "MacBook Pro",
    "devices": [
      "MacBookPro1,1"
    ],
    "order": 0
  },
  "MacBook Pro (17-inch, Early 2006)": {
    "name": "MacBook Pro (17-inch, Early 2006)",
    "type": "MacBook Pro",
    "devices": [
      "MacBookPro1,2"
    ],
    "order": 1
  },
  "MacBook Pro (Retina, 15-inch, Early 2013)": {
    "name": "MacBook Pro (Retina, 15-inch, Early 2013)",
    "type": "MacBook Pro",
    "devices": [
      "MacBookPro10,1-Early-2013"
    ],
    "order": 2
  },
  "MacBook Pro (Retina, 15-inch, Mid 2012)": {
    "name": "MacBook Pro (Retina, 15-inch, Mid 2012)",
    "type": "MacBook Pro",
    "devices": [
      "MacBookPro10,1-Mid-2012"
    ],
    "order": 3
  },
  "MacBook Pro (Retina, 13-inch, Early 2013)": {
    "name": "MacBook Pro (Retina, 13-inch, Early 2013)",
    "type": "MacBook Pro",
    "devices": [
      "MacBookPro10,2-Early-2013"
    ],
    "order": 4
  },
  "MacBook Pro (Retina, 13-inch, Late 2012)": {
    "name": "MacBook Pro (Retina, 13-inch, Late 2012)",
    "type": "MacBook Pro",
    "devices": [
      "MacBookPro10,2-Late-2012"
    ],
    "order": 5
  },
  "MacBook Pro (Retina, 13-inch, Late 2013)": {
    "name": "MacBook Pro (Retina, 13-inch, Late 2013)",
    "type": "MacBook Pro",
    "devices": [
      "MacBookPro11,1-Late-2013"
    ],
    "order": 6
  },
  "MacBook Pro (Retina, 13-inch, Mid 2014)": {
    "name": "MacBook Pro (Retina, 13-inch, Mid 2014)",
    "type": "MacBook Pro",
    "devices": [
      "MacBookPro11,1-Mid-2014"
    ],
    "order": 7
  },
  "MacBook Pro (Retina, 13-inch, Early 2015)": {
    "name": "MacBook Pro (Retina, 13-inch, Early 2015)",
    "type": "MacBook Pro",
    "devices": [
      "MacBookPro12,1"
    ],
    "order": 8
  },
  "MacBook Pro (15-inch, 2016)": {
    "name": "MacBook Pro (15-inch, 2016)",
    "type": "MacBook Pro",
    "devices": [
      "MacBookPro13,3"
    ],
    "order": 9
  },
  "MacBook Pro (15-inch, 2017)": {
    "name": "MacBook Pro (15-inch, 2017)",
    "type": "MacBook Pro",
    "devices": [
      "MacBookPro14,3"
    ],
    "order": 10
  },
  "MacBook Pro (13-inch, 2018)": {
    "name": "MacBook Pro (13-inch, 2018)",
    "type": "MacBook Pro",
    "devices": [
      "MacBookPro15,2-2018"
    ],
    "order": 11
  },
  "MacBook Pro (M1, Late 2020)": {
    "name": "MacBook Pro (M1, Late 2020)",
    "type": "MacBook Pro",
    "devices": [
      "MacBookPro17,1"
    ],
    "order": 12
  },
  "MacBook Pro (17-inch, Late 2006)": {
    "name": "MacBook Pro (17-inch, Late 2006)",
    "type": "MacBook Pro",
    "devices": [
      "MacBookPro2,1"
    ],
    "order": 13
  },
  "MacBook Pro (15-inch, Late 2006)": {
    "name": "MacBook Pro (15-inch, Late 2006)",
    "type": "MacBook Pro",
    "devices": [
      "MacBookPro2,2"
    ],
    "order": 14
  },
  "MacBook Pro (15-inch, Late 2007)": {
    "name": "MacBook Pro (15-inch, Late 2007)",
    "type": "MacBook Pro",
    "devices": [
      "MacBookPro3,1-15-inch-Late-2007"
    ],
    "order": 15
  },
  "MacBook Pro (15-inch, Mid 2007)": {
    "name": "MacBook Pro (15-inch, Mid 2007)",
    "type": "MacBook Pro",
    "devices": [
      "MacBookPro3,1-15-inch-Mid-2007"
    ],
    "order": 16
  },
  "MacBook Pro (17-inch, Mid 2007)": {
    "name": "MacBook Pro (17-inch, Mid 2007)",
    "type": "MacBook Pro",
    "devices": [
      "MacBookPro3,1-17-inch"
    ],
    "order": 17
  },
  "MacBook Pro (15-inch, Early 2008)": {
    "name": "MacBook Pro (15-inch, Early 2008)",
    "type": "MacBook Pro",
    "devices": [
      "MacBookPro4,1-15-inch"
    ],
    "order": 18
  },
  "MacBook Pro (17-inch, Early 2008)": {
    "name": "MacBook Pro (17-inch, Early 2008)",
    "type": "MacBook Pro",
    "devices": [
      "MacBookPro4,1-17-inch"
    ],
    "order": 19
  },
  "MacBook Pro (15-inch, Late 2008)": {
    "name": "MacBook Pro (15-inch, Late 2008)",
    "type": "MacBook Pro",
    "devices": [
      "MacBookPro5,1-2008"
    ],
    "order": 20
  },
  "MacBook Pro (15-inch, Early 2009)": {
    "name": "MacBook Pro (15-inch, Early 2009)",
    "type": "MacBook Pro",
    "devices": [
      "MacBookPro5,1-2009"
    ],
    "order": 21
  },
  "MacBook Pro (17-inch, Early 2009)": {
    "name": "MacBook Pro (17-inch, Early 2009)",
    "type": "MacBook Pro",
    "devices": [
      "MacBookPro5,2-Early-2009"
    ],
    "order": 22
  },
  "MacBook Pro (17-inch, Mid 2009)": {
    "name": "MacBook Pro (17-inch, Mid 2009)",
    "type": "MacBook Pro",
    "devices": [
      "MacBookPro5,2-Mid-2009"
    ],
    "order": 23
  },
  "MacBook Pro (15-inch, Mid 2009)": {
    "name": "MacBook Pro (15-inch, Mid 2009)",
    "type": "MacBook Pro",
    "devices": [
      "MacBookPro5,4"
    ],
    "order": 25
  },
  "MacBook Pro (13-inch, Mid 2009)": {
    "name": "MacBook Pro (13-inch, Mid 2009)",
    "type": "MacBook Pro",
    "devices": [
      "MacBookPro5,5"
    ],
    "order": 26
  },
  "MacBook Pro (17-inch, Mid 2010)": {
    "name": "MacBook Pro (17-inch, Mid 2010)",
    "type": "MacBook Pro",
    "devices": [
      "MacBookPro6,1"
    ],
    "order": 27
  },
  "MacBook Pro (15-inch, Mid 2010)": {
    "name": "MacBook Pro (15-inch, Mid 2010)",
    "type": "MacBook Pro",
    "devices": [
      "MacBookPro6,2"
    ],
    "order": 28
  },
  "MacBook Pro (13-inch, Mid 2010)": {
    "name": "MacBook Pro (13-inch, Mid 2010)",
    "type": "MacBook Pro",
    "devices": [
      "MacBookPro7,1"
    ],
    "order": 29
  },
  "MacBook Pro (13-inch, Early 2011)": {
    "name": "MacBook Pro (13-inch, Early 2011)",
    "type": "MacBook Pro",
    "devices": [
      "MacBookPro8,1-Early-2011"
    ],
    "order": 30
  },
  "MacBook Pro (13-inch, Late 2011)": {
    "name": "MacBook Pro (13-inch, Late 2011)",
    "type": "MacBook Pro",
    "devices": [
      "MacBookPro8,1-Late-2011"
    ],
    "order": 31
  },
  "MacBook Pro (15-inch, Early 2011)": {
    "name": "MacBook Pro (15-inch, Early 2011)",
    "type": "MacBook Pro",
    "devices": [
      "MacBookPro8,2-Early-2011"
    ],
    "order": 32
  },
  "MacBook Pro (15-inch, Late 2011)": {
    "name": "MacBook Pro (15-inch, Late 2011)",
    "type": "MacBook Pro",
    "devices": [
      "MacBookPro8,2-Late-2011"
    ],
    "order": 33
  },
  "MacBook Pro (17-inch, Early 2011)": {
    "name": "MacBook Pro (17-inch, Early 2011)",
    "type": "MacBook Pro",
    "devices": [
      "MacBookPro8,3-Early-2011"
    ],
    "order": 34
  },
  "MacBook Pro (17-inch, Late 2011)": {
    "name": "MacBook Pro (17-inch, Late 2011)",
    "type": "MacBook Pro",
    "devices": [
      "MacBookPro8,3-Late-2011"
    ],
    "order": 35
  },
  "MacBook Pro (15-inch, Mid 2012)": {
    "name": "MacBook Pro (15-inch, Mid 2012)",
    "type": "MacBook Pro",
    "devices": [
      "MacBookPro9,1"
    ],
    "order": 36
  },
  "MacBook Pro (13-inch, Mid 2012)": {
    "name": "MacBook Pro (13-inch, Mid 2012)",
    "type": "MacBook Pro",
    "devices": [
      "MacBookPro9,2"
    ],
    "order": 37
  },
  "Mac mini (Early 2006)": {
    "name": "Mac mini (Early 2006)",
    "type": "Mac mini",
    "devices": [
      "Macmini1,1-Early-2006"
    ],
    "order": 0
  },
  "Mac mini (Late 2006)": {
    "name": "Mac mini (Late 2006)",
    "type": "Mac mini",
    "devices": [
      "Macmini1,1-Late-2006"
    ],
    "order": 1
  },
  "Mac mini (Mid 2007)": {
    "name": "Mac mini (Mid 2007)",
    "type": "Mac mini",
    "devices": [
      "Macmini2,1"
    ],
    "order": 2
  },
  "Mac mini (Early 2009)": {
    "name": "Mac mini (Early 2009)",
    "type": "Mac mini",
    "devices": [
      "Macmini3,1-Early-2009"
    ],
    "order": 3
  },
  "Mac mini (Late 2009)": {
    "name": "Mac mini (Late 2009)",
    "type": "Mac mini",
    "devices": [
      "Macmini3,1-Late-2009"
    ],
    "order": 4
  },
  "Mac mini (Mid 2010)": {
    "name": "Mac mini (Mid 2010)",
    "type": "Mac mini",
    "devices": [
      "Macmini4,1"
    ],
    "order": 5
  },
  "Mac mini (Late 2014)": {
    "name": "Mac mini (Late 2014)",
    "type": "Mac mini",
    "devices": [
      "Macmini7,1"
    ],
    "order": 6
  },
  "Mac mini (Late 2018)": {
    "name": "Mac mini (Late 2018)",
    "type": "Mac mini",
    "devices": [
      "Macmini8,1"
    ],
    "order": 7
  },
  "Mac mini (M1, Late 2020)": {
    "name": "Mac mini (M1, Late 2020)",
    "type": "Mac mini",
    "devices": [
      "Macmini9,1"
    ],
    "order": 8
  },
  "Magic Mouse (1st generation)": {
    "name": "Magic Mouse (1st generation)",
    "type": "Mouse",
    "devices": [
      "Magic Mouse (1st generation)"
    ],
    "order": 0
  },
  "Magic Mouse (3rd generation)": {
    "name": "Magic Mouse (3rd generation)",
    "type": "Mouse",
    "devices": [
      "Magic Mouse (3rd generation)"
    ],
    "order": 1
  },
  "Magic Mouse 2": {
    "name": "Magic Mouse 2",
    "type": "Mouse",
    "devices": [
      "Magic Mouse 2"
    ],
    "order": 2
  },
  "MagSafe Battery Pack": {
    "name": "MagSafe Battery Pack",
    "type": "Power",
    "devices": [
      "MagSafe Battery Pack"
    ],
    "order": 0
  },
  "iPhone 11 Pro Max Smart Battery Case": {
    "name": "iPhone 11 Pro Max Smart Battery Case",
    "type": "Power",
    "devices": [
      "iPhone 11 Pro Max Smart Battery Case"
    ],
    "order": 1
  },
  "iPhone 11 Pro Smart Battery Case": {
    "name": "iPhone 11 Pro Smart Battery Case",
    "type": "Power",
    "devices": [
      "iPhone 11 Pro Smart Battery Case"
    ],
    "order": 2
  },
  "iPhone 11 Smart Battery Case": {
    "name": "iPhone 11 Smart Battery Case",
    "type": "Power",
    "devices": [
      "iPhone 11 Smart Battery Case"
    ],
    "order": 3
  },
  "iPhone 6s Smart Battery Case": {
    "name": "iPhone 6s Smart Battery Case",
    "type": "Power",
    "devices": [
      "iPhone 6s Smart Battery Case"
    ],
    "order": 4
  },
  "iPhone 7 Smart Battery Case": {
    "name": "iPhone 7 Smart Battery Case",
    "type": "Power",
    "devices": [
      "iPhone 7 Smart Battery Case"
    ],
    "order": 5
  },
  "iPhone XR Smart Battery Case": {
    "name": "iPhone XR Smart Battery Case",
    "type": "Power",
    "devices": [
      "iPhone XR Smart Battery Case"
    ],
    "order": 6
  },
  "iPhone XS Max Smart Battery Case": {
    "name": "iPhone XS Max Smart Battery Case",
    "type": "Power",
    "devices": [
      "iPhone XS Max Smart Battery Case"
    ],
    "order": 7
  },
  "iPhone XS Smart Battery Case": {
    "name": "iPhone XS Smart Battery Case",
    "type": "Power",
    "devices": [
      "iPhone XS Smart Battery Case"
    ],
    "order": 8
  },
  "10W USB Power Adapter": {
    "name": "10W USB Power Adapter",
    "type": "Power",
    "devices": [
      "10W USB Power Adapter"
    ],
    "order": 9
  },
  "12W USB Power Adapter (AUS)": {
    "name": "12W USB Power Adapter (AUS)",
    "type": "Power",
    "devices": [
      "12W USB Power Adapter (AUS)"
    ],
    "order": 10
  },
  "12W USB Power Adapter (USA)": {
    "name": "12W USB Power Adapter (USA)",
    "type": "Power",
    "devices": [
      "12W USB Power Adapter (USA)"
    ],
    "order": 11
  },
  "140W USB-C Power Adapter": {
    "name": "140W USB-C Power Adapter",
    "type": "Power",
    "devices": [
      "140W USB-C Power Adapter"
    ],
    "order": 12
  },
  "18W USB-C Power Adapter (AUS)": {
    "name": "18W USB-C Power Adapter (AUS)",
    "type": "Power",
    "devices": [
      "18W USB-C Power Adapter (AUS)"
    ],
    "order": 13
  },
  "18W USB-C Power Adapter (CHN)": {
    "name": "18W USB-C Power Adapter (CHN)",
    "type": "Power",
    "devices": [
      "18W USB-C Power Adapter (CHN)"
    ],
    "order": 14
  },
  "18W USB-C Power Adapter (EUR)": {
    "name": "18W USB-C Power Adapter (EUR)",
    "type": "Power",
    "devices": [
      "18W USB-C Power Adapter (EUR)"
    ],
    "order": 15
  },
  "18W USB-C Power Adapter (GBR)": {
    "name": "18W USB-C Power Adapter (GBR)",
    "type": "Power",
    "devices": [
      "18W USB-C Power Adapter (GBR)"
    ],
    "order": 16
  },
  "18W USB-C Power Adapter (KOR)": {
    "name": "18W USB-C Power Adapter (KOR)",
    "type": "Power",
    "devices": [
      "18W USB-C Power Adapter (KOR)"
    ],
    "order": 17
  },
  "18W USB-C Power Adapter (USA)": {
    "name": "18W USB-C Power Adapter (USA)",
    "type": "Power",
    "devices": [
      "18W USB-C Power Adapter (USA)"
    ],
    "order": 18
  },
  "20W USB-C Power Adapter (GBR)": {
    "name": "20W USB-C Power Adapter (GBR)",
    "type": "Power",
    "devices": [
      "20W USB-C Power Adapter (GBR)"
    ],
    "order": 19
  },
  "20W USB-C Power Adapter (USA)": {
    "name": "20W USB-C Power Adapter (USA)",
    "type": "Power",
    "devices": [
      "20W USB-C Power Adapter (USA)"
    ],
    "order": 20
  },
  "29W USB-C Power Adapter": {
    "name": "29W USB-C Power Adapter",
    "type": "Power",
    "devices": [
      "29W USB-C Power Adapter"
    ],
    "order": 21
  },
  "30W USB-C Power Adapter": {
    "name": "30W USB-C Power Adapter",
    "type": "Power",
    "devices": [
      "30W USB-C Power Adapter"
    ],
    "order": 23
  },
  "35W Dual USB-C Port Compact Power Adapter": {
    "name": "35W Dual USB-C Port Compact Power Adapter",
    "type": "Power",
    "devices": [
      "35W Dual USB-C Port Compact Power Adapter"
    ],
    "order": 24
  },
  "35W Dual USB-C Port Power Adapter": {
    "name": "35W Dual USB-C Port Power Adapter",
    "type": "Power",
    "devices": [
      "35W Dual USB-C Port Power Adapter"
    ],
    "order": 25
  },
  "45W MagSafe 2 Power Adapter": {
    "name": "45W MagSafe 2 Power Adapter",
    "type": "Power",
    "devices": [
      "45W MagSafe 2 Power Adapter"
    ],
    "order": 26
  },
  "45W MagSafe Power Adapter with \"L\" style connector": {
    "name": "45W MagSafe Power Adapter with \"L\" style connector",
    "type": "Power",
    "devices": [
      "45W MagSafe Power Adapter with \"L\" style connector"
    ],
    "order": 27
  },
  "5W USB Power Adapter (ARG)": {
    "name": "5W USB Power Adapter (ARG)",
    "type": "Power",
    "devices": [
      "5W USB Power Adapter (ARG)"
    ],
    "order": 28
  },
  "5W USB Power Adapter (AUS)": {
    "name": "5W USB Power Adapter (AUS)",
    "type": "Power",
    "devices": [
      "5W USB Power Adapter (AUS)"
    ],
    "order": 32
  },
  "5W USB Power Adapter (CHN)": {
    "name": "5W USB Power Adapter (CHN)",
    "type": "Power",
    "devices": [
      "5W USB Power Adapter (CHN)"
    ],
    "order": 30
  },
  "5W USB Power Adapter (GBR)": {
    "name": "5W USB Power Adapter (GBR)",
    "type": "Power",
    "devices": [
      "5W USB Power Adapter (GBR)"
    ],
    "order": 33
  },
  "5W USB Power Adapter (USA)": {
    "name": "5W USB Power Adapter (USA)",
    "type": "Power",
    "devices": [
      "5W USB Power Adapter (USA)"
    ],
    "order": 34
  },
  "5W USB Power Adapter for iPod & iPhone": {
    "name": "5W USB Power Adapter for iPod & iPhone",
    "type": "Power",
    "devices": [
      "5W USB Power Adapter for iPod & iPhone"
    ],
    "order": 35
  },
  "5W USB Power Adapter": {
    "name": "5W USB Power Adapter",
    "type": "Power",
    "devices": [
      "5W USB Power Adapter"
    ],
    "order": 36
  },
  "60W MagSafe 2 Power Adapter": {
    "name": "60W MagSafe 2 Power Adapter",
    "type": "Power",
    "devices": [
      "60W MagSafe 2 Power Adapter"
    ],
    "order": 37
  },
  "60W MagSafe Power Adapter with \"L\" style connector": {
    "name": "60W MagSafe Power Adapter with \"L\" style connector",
    "type": "Power",
    "devices": [
      "60W MagSafe Power Adapter with \"L\" style connector"
    ],
    "order": 38
  },
  "60W MagSafe Power Adapter with \"T\" style connector": {
    "name": "60W MagSafe Power Adapter with \"T\" style connector",
    "type": "Power",
    "devices": [
      "60W MagSafe Power Adapter with \"T\" style connector"
    ],
    "order": 39
  },
  "61W USB-C Power Adapter": {
    "name": "61W USB-C Power Adapter",
    "type": "Power",
    "devices": [
      "61W USB-C Power Adapter"
    ],
    "order": 41
  },
  "67W USB-C Power Adapter": {
    "name": "67W USB-C Power Adapter",
    "type": "Power",
    "devices": [
      "67W USB-C Power Adapter"
    ],
    "order": 42
  },
  "85W MagSafe 2 Power Adapter": {
    "name": "85W MagSafe 2 Power Adapter",
    "type": "Power",
    "devices": [
      "85W MagSafe 2 Power Adapter"
    ],
    "order": 43
  },
  "85W MagSafe Power Adapter with \"L\" style connector": {
    "name": "85W MagSafe Power Adapter with \"L\" style connector",
    "type": "Power",
    "devices": [
      "85W MagSafe Power Adapter with \"L\" style connector"
    ],
    "order": 44
  },
  "85W MagSafe Power Adapter with \"T\" style connector": {
    "name": "85W MagSafe Power Adapter with \"T\" style connector",
    "type": "Power",
    "devices": [
      "85W MagSafe Power Adapter with \"T\" style connector"
    ],
    "order": 45
  },
  "87W USB-C Power Adapter": {
    "name": "87W USB-C Power Adapter",
    "type": "Power",
    "devices": [
      "87W USB-C Power Adapter"
    ],
    "order": 46
  },
  "96W USB-C Power Adapter": {
    "name": "96W USB-C Power Adapter",
    "type": "Power",
    "devices": [
      "96W USB-C Power Adapter"
    ],
    "order": 47
  },
  "Apple World Travel Adapter Kit (AUS)": {
    "name": "Apple World Travel Adapter Kit (AUS)",
    "type": "Power",
    "devices": [
      "Apple World Travel Adapter Kit (AUS)"
    ],
    "order": 48
  },
  "Apple World Travel Adapter Kit (BRA)": {
    "name": "Apple World Travel Adapter Kit (BRA)",
    "type": "Power",
    "devices": [
      "Apple World Travel Adapter Kit (BRA)"
    ],
    "order": 49
  },
  "Apple World Travel Adapter Kit (CHN)": {
    "name": "Apple World Travel Adapter Kit (CHN)",
    "type": "Power",
    "devices": [
      "Apple World Travel Adapter Kit (CHN)"
    ],
    "order": 50
  },
  "Apple World Travel Adapter Kit (EUR)": {
    "name": "Apple World Travel Adapter Kit (EUR)",
    "type": "Power",
    "devices": [
      "Apple World Travel Adapter Kit (EUR)"
    ],
    "order": 51
  },
  "Apple World Travel Adapter Kit (GBR)": {
    "name": "Apple World Travel Adapter Kit (GBR)",
    "type": "Power",
    "devices": [
      "Apple World Travel Adapter Kit (GBR)"
    ],
    "order": 52
  },
  "Apple World Travel Adapter Kit (KOR)": {
    "name": "Apple World Travel Adapter Kit (KOR)",
    "type": "Power",
    "devices": [
      "Apple World Travel Adapter Kit (KOR)"
    ],
    "order": 53
  },
  "Apple World Travel Adapter Kit (USA)": {
    "name": "Apple World Travel Adapter Kit (USA)",
    "type": "Power",
    "devices": [
      "Apple World Travel Adapter Kit (USA)"
    ],
    "order": 54
  },
  "iPod USB Power Adapter": {
    "name": "iPod USB Power Adapter",
    "type": "Power",
    "devices": [
      "iPod USB Power Adapter"
    ],
    "order": 55
  },
  "Apple Watch Magnetic Charging Dock": {
    "name": "Apple Watch Magnetic Charging Dock",
    "type": "Power",
    "devices": [
      "Apple Watch Magnetic Charging Dock"
    ],
    "order": 56
  },
  "MagSafe Charger": {
    "name": "MagSafe Charger",
    "type": "Power",
    "devices": [
      "MagSafe Charger"
    ],
    "order": 57
  },
  "MagSafe Duo Charger": {
    "name": "MagSafe Duo Charger",
    "type": "Power",
    "devices": [
      "MagSafe Duo Charger"
    ],
    "order": 58
  },
  "Apple Watch Magnetic Charging Cable (USB-C)": {
    "name": "Apple Watch Magnetic Charging Cable (USB-C)",
    "type": "Power",
    "devices": [
      "Apple Watch Magnetic Charging Cable (USB-C)"
    ],
    "order": 59
  },
  "Apple Watch Magnetic Fast Charger to USB-C Cable": {
    "name": "Apple Watch Magnetic Fast Charger to USB-C Cable",
    "type": "Power",
    "devices": [
      "Apple Watch Magnetic Fast Charger to USB-C Cable"
    ],
    "order": 60
  },
  "Lightning to USB Cable (0.5m)": {
    "name": "Lightning to USB Cable (0.5m)",
    "type": "Power",
    "devices": [
      "Lightning to USB Cable (0.5m)"
    ],
    "order": 61
  },
  "Lightning to USB Cable (1m)": {
    "name": "Lightning to USB Cable (1m)",
    "type": "Power",
    "devices": [
      "Lightning to USB Cable (1m)"
    ],
    "order": 63
  },
  "MagSafe to MagSafe 2 Converter": {
    "name": "MagSafe to MagSafe 2 Converter",
    "type": "Power",
    "devices": [
      "MagSafe to MagSafe 2 Converter"
    ],
    "order": 64
  },
  "Thunderbolt 4 Pro Cable (1.8 m)": {
    "name": "Thunderbolt 4 Pro Cable (1.8 m)",
    "type": "Power",
    "devices": [
      "Thunderbolt 4 Pro Cable (1.8 m)"
    ],
    "order": 65
  },
  "Thunderbolt 4 Pro Cable (3m)": {
    "name": "Thunderbolt 4 Pro Cable (3m)",
    "type": "Power",
    "devices": [
      "Thunderbolt 4 Pro Cable (3m)"
    ],
    "order": 66
  },
  "USB-C to MagSafe 3 Cable (2 m)": {
    "name": "USB-C to MagSafe 3 Cable (2 m)",
    "type": "Power",
    "devices": [
      "USB-C to MagSafe 3 Cable (2 m)"
    ],
    "order": 67
  },
  "Mac mini (Early 2005)": {
    "name": "Mac mini (Early 2005)",
    "type": "Mac mini",
    "devices": [
      "PowerMac10,1"
    ],
    "order": 0
  },
  "Mac mini (Late 2005)": {
    "name": "Mac mini (Late 2005)",
    "type": "Mac mini",
    "devices": [
      "PowerMac10,2"
    ],
    "order": 1
  },
  "Apple Remote (aluminum)": {
    "name": "Apple Remote (aluminum)",
    "type": "Remote",
    "devices": [
      "Apple Remote (aluminum)"
    ],
    "order": 0
  },
  "Apple Remote (white)": {
    "name": "Apple Remote (white)",
    "type": "Remote",
    "devices": [
      "Apple Remote (white)"
    ],
    "order": 1
  },
  "Siri Remote (1st generation)": {
    "name": "Siri Remote (1st generation)",
    "type": "Remote",
    "devices": [
      "ATVRemote1,1"
    ],
    "order": 2
  },
  "Siri Remote (1st generation, Rev A)": {
    "name": "Siri Remote (1st generation, Rev A)",
    "type": "Remote",
    "devices": [
      "ATVRemote1,2"
    ],
    "order": 3
  },
  "Siri Remote (2nd generation)": {
    "name": "Siri Remote (2nd generation)",
    "type": "Remote",
    "devices": [
      "Siri Remote (2nd generation)"
    ],
    "order": 4
  },
  "Magic Trackpad (1st generation)": {
    "name": "Magic Trackpad (1st generation)",
    "type": "Trackpad",
    "devices": [
      "Magic Trackpad (1st generation)"
    ],
    "order": 0
  },
  "Magic Trackpad (3rd generation)": {
    "name": "Magic Trackpad (3rd generation)",
    "type": "Trackpad",
    "devices": [
      "Magic Trackpad (3rd generation)"
    ],
    "order": 1
  },
  "Magic Trackpad 2": {
    "name": "Magic Trackpad 2",
    "type": "Trackpad",
    "devices": [
      "Magic Trackpad 2"
    ],
    "order": 2
  },
  "iMac (21.5-inch, Late 2009)": {
    "name": "iMac (21.5-inch, Late 2009)",
    "type": "iMac",
    "devices": [
      "iMac10,1-21.5-inch"
    ],
    "order": 0
  },
  "iMac (27-inch, Late 2009)": {
    "name": "iMac (27-inch, Late 2009)",
    "type": "iMac",
    "devices": [
      "iMac10,1-27-inch"
    ],
    "order": 1
  },
  "iMac (21.5-inch, Mid 2010)": {
    "name": "iMac (21.5-inch, Mid 2010)",
    "type": "iMac",
    "devices": [
      "iMac11,2"
    ],
    "order": 2
  },
  "iMac (27-inch, Mid 2010)": {
    "name": "iMac (27-inch, Mid 2010)",
    "type": "iMac",
    "devices": [
      "iMac11,3"
    ],
    "order": 3
  },
  "iMac (21.5-inch, Late 2011)": {
    "name": "iMac (21.5-inch, Late 2011)",
    "type": "iMac",
    "devices": [
      "iMac12,1-Late-2011"
    ],
    "order": 4
  },
  "iMac (21.5-inch, Mid 2011)": {
    "name": "iMac (21.5-inch, Mid 2011)",
    "type": "iMac",
    "devices": [
      "iMac12,1-Mid-2011"
    ],
    "order": 5
  },
  "iMac (27-inch, Mid 2011)": {
    "name": "iMac (27-inch, Mid 2011)",
    "type": "iMac",
    "devices": [
      "iMac12,2"
    ],
    "order": 6
  },
  "iMac (21.5-inch, Early 2013)": {
    "name": "iMac (21.5-inch, Early 2013)",
    "type": "iMac",
    "devices": [
      "iMac13,1-Early-2013"
    ],
    "order": 7
  },
  "iMac (21.5-inch, Late 2012)": {
    "name": "iMac (21.5-inch, Late 2012)",
    "type": "iMac",
    "devices": [
      "iMac13,1-Late-2012"
    ],
    "order": 8
  },
  "iMac (27-inch, Late 2012)": {
    "name": "iMac (27-inch, Late 2012)",
    "type": "iMac",
    "devices": [
      "iMac13,2"
    ],
    "order": 9
  },
  "iMac (21.5-inch, Late 2013)": {
    "name": "iMac (21.5-inch, Late 2013)",
    "type": "iMac",
    "devices": [
      "iMac14,1"
    ],
    "order": 10
  },
  "iMac (27-inch, Late 2013)": {
    "name": "iMac (27-inch, Late 2013)",
    "type": "iMac",
    "devices": [
      "iMac14,2"
    ],
    "order": 11
  },
  "iMac (21.5-inch, Mid 2014)": {
    "name": "iMac (21.5-inch, Mid 2014)",
    "type": "iMac",
    "devices": [
      "iMac14,4"
    ],
    "order": 12
  },
  "iMac (Retina 5K, 27-inch, Late 2014)": {
    "name": "iMac (Retina 5K, 27-inch, Late 2014)",
    "type": "iMac",
    "devices": [
      "iMac15,1-Late-2014"
    ],
    "order": 13
  },
  "iMac (Retina 5K, 27-inch, Mid 2015)": {
    "name": "iMac (Retina 5K, 27-inch, Mid 2015)",
    "type": "iMac",
    "devices": [
      "iMac15,1-Mid-2015"
    ],
    "order": 14
  },
  "iMac (21.5-inch, Late 2015)": {
    "name": "iMac (21.5-inch, Late 2015)",
    "type": "iMac",
    "devices": [
      "iMac16,2"
    ],
    "order": 17
  },
  "iMac (Retina 4K, 21.5-inch, Late 2015)": {
    "name": "iMac (Retina 4K, 21.5-inch, Late 2015)",
    "type": "iMac",
    "devices": [
      "iMac16,2-4K"
    ],
    "order": 16
  },
  "iMac (Retina 5K, 27-inch, Late 2015)": {
    "name": "iMac (Retina 5K, 27-inch, Late 2015)",
    "type": "iMac",
    "devices": [
      "iMac17,1"
    ],
    "order": 18
  },
  "iMac (21.5-inch, 2017)": {
    "name": "iMac (21.5-inch, 2017)",
    "type": "iMac",
    "devices": [
      "iMac18,1"
    ],
    "order": 19
  },
  "iMac (Retina 4K, 21.5-inch, 2017)": {
    "name": "iMac (Retina 4K, 21.5-inch, 2017)",
    "type": "iMac",
    "devices": [
      "iMac18,2"
    ],
    "order": 20
  },
  "iMac (Retina 5K, 27-inch, 2017)": {
    "name": "iMac (Retina 5K, 27-inch, 2017)",
    "type": "iMac",
    "devices": [
      "iMac18,3"
    ],
    "order": 21
  },
  "iMac (Retina 5K, 27-inch, 2019)": {
    "name": "iMac (Retina 5K, 27-inch, 2019)",
    "type": "iMac",
    "devices": [
      "iMac19,1"
    ],
    "order": 22
  },
  "iMac (Retina 4K, 21.5-inch, 2019)": {
    "name": "iMac (Retina 4K, 21.5-inch, 2019)",
    "type": "iMac",
    "devices": [
      "iMac19,2"
    ],
    "order": 23
  },
  "iMac (20-inch, Mid 2007)": {
    "name": "iMac (20-inch, Mid 2007)",
    "type": "iMac",
    "devices": [
      "iMac7,1-20-inch"
    ],
    "order": 24
  },
  "iMac (24-inch, Mid 2007)": {
    "name": "iMac (24-inch, Mid 2007)",
    "type": "iMac",
    "devices": [
      "iMac7,1-24-inch"
    ],
    "order": 25
  },
  "iMac (20-inch, Early 2008)": {
    "name": "iMac (20-inch, Early 2008)",
    "type": "iMac",
    "devices": [
      "iMac8,1-20-inch"
    ],
    "order": 26
  },
  "iMac (24-inch, Early 2008)": {
    "name": "iMac (24-inch, Early 2008)",
    "type": "iMac",
    "devices": [
      "iMac8,1-24-inch"
    ],
    "order": 27
  },
  "iMac (20-inch, Early 2009)": {
    "name": "iMac (20-inch, Early 2009)",
    "type": "iMac",
    "devices": [
      "iMac9,1-20-inch-Early-2009"
    ],
    "order": 28
  },
  "iMac (20-inch, Mid 2009)": {
    "name": "iMac (20-inch, Mid 2009)",
    "type": "iMac",
    "devices": [
      "iMac9,1-20-inch-Mid-2009"
    ],
    "order": 29
  },
  "iMac (24-inch, Early 2009)": {
    "name": "iMac (24-inch, Early 2009)",
    "type": "iMac",
    "devices": [
      "iMac9,1-24-inch"
    ],
    "order": 30
  },
  "iPad": {
    "name": "iPad",
    "type": "iPad",
    "devices": [
      "iPad1,1"
    ],
    "order": 0
  },
  "iPhone 3G": {
    "name": "iPhone 3G",
    "type": "iPhone",
    "devices": [
      "iPhone1,2"
    ],
    "order": 0
  },
  "iPhone XR": {
    "name": "iPhone XR",
    "type": "iPhone",
    "devices": [
      "iPhone11,8"
    ],
    "order": 1
  },
  "iPhone 11": {
    "name": "iPhone 11",
    "type": "iPhone",
    "devices": [
      "iPhone12,1"
    ],
    "order": 2
  },
  "iPhone SE (2nd generation)": {
    "name": "iPhone SE (2nd generation)",
    "type": "iPhone",
    "devices": [
      "iPhone12,8"
    ],
    "order": 3
  },
  "iPhone SE (3rd generation)": {
    "name": "iPhone SE (3rd generation)",
    "type": "iPhone",
    "devices": [
      "iPhone14,6"
    ],
    "order": 4
  },
  "iPhone 3GS": {
    "name": "iPhone 3GS",
    "type": "iPhone",
    "devices": [
      "iPhone2,1"
    ],
    "order": 5
  },
  "iPhone 4S": {
    "name": "iPhone 4S",
    "type": "iPhone",
    "devices": [
      "iPhone4,1"
    ],
    "order": 6
  },
  "iPhone SE (1st generation)": {
    "name": "iPhone SE (1st generation)",
    "type": "iPhone",
    "devices": [
      "iPhone8,4"
    ],
    "order": 7
  },
  "iPod (Click Wheel)": {
    "name": "iPod (Click Wheel)",
    "type": "iPod",
    "devices": [
      "iPod (Click Wheel)"
    ],
    "order": 0
  },
  "iPod (Dock Connector)": {
    "name": "iPod (Dock Connector)",
    "type": "iPod",
    "devices": [
      "iPod (Dock Connector)"
    ],
    "order": 1
  },
  "iPod (Scroll Wheel)": {
    "name": "iPod (Scroll Wheel)",
    "type": "iPod",
    "devices": [
      "iPod (Scroll Wheel)"
    ],
    "order": 2
  },
  "iPod (Touch Wheel)": {
    "name": "iPod (Touch Wheel)",
    "type": "iPod",
    "devices": [
      "iPod (Touch Wheel)"
    ],
    "order": 3
  },
  "iPod shuffle (2nd generation)": {
    "name": "iPod shuffle (2nd generation)",
    "type": "iPod shuffle",
    "devices": [
      "iPod shuffle (2nd generation)"
    ],
    "order": 0
  },
  "iPod shuffle": {
    "name": "iPod shuffle",
    "type": "iPod shuffle",
    "devices": [
      "iPod shuffle"
    ],
    "order": 1
  },
  "iPod mini (2nd generation)": {
    "name": "iPod mini (2nd generation)",
    "type": "iPod mini",
    "devices": [
      "iPod mini (2nd generation)"
    ],
    "order": 0
  },
  "iPod mini": {
    "name": "iPod mini",
    "type": "iPod mini",
    "devices": [
      "iPod mini"
    ],
    "order": 1
  },
  "iPod nano (2nd generation)": {
    "name": "iPod nano (2nd generation)",
    "type": "iPod nano",
    "devices": [
      "iPod nano (2nd generation)"
    ],
    "order": 0
  },
  "iPod nano (3rd generation)": {
    "name": "iPod nano (3rd generation)",
    "type": "iPod nano",
    "devices": [
      "iPod nano (3rd generation)"
    ],
    "order": 1
  },
  "iPod nano (4th generation)": {
    "name": "iPod nano (4th generation)",
    "type": "iPod nano",
    "devices": [
      "iPod nano (4th generation)"
    ],
    "order": 2
  },
  "iPod nano (5th generation)": {
    "name": "iPod nano (5th generation)",
    "type": "iPod nano",
    "devices": [
      "iPod nano (5th generation)"
    ],
    "order": 3
  },
  "iPod nano (6th generation)": {
    "name": "iPod nano (6th generation)",
    "type": "iPod nano",
    "devices": [
      "iPod nano (6th generation)"
    ],
    "order": 4
  },
  "iPod nano": {
    "name": "iPod nano",
    "type": "iPod nano",
    "devices": [
      "iPod nano"
    ],
    "order": 5
  },
  "iPod touch (1st generation)": {
    "name": "iPod touch (1st generation)",
    "type": "iPod touch",
    "devices": [
      "iPod1,1"
    ],
    "order": 0
  },
  "iPod touch (2nd generation)": {
    "name": "iPod touch (2nd generation)",
    "type": "iPod touch",
    "devices": [
      "iPod2,1"
    ],
    "order": 1
  },
  "iPod touch (3rd generation)": {
    "name": "iPod touch (3rd generation)",
    "type": "iPod touch",
    "devices": [
      "iPod3,1"
    ],
    "order": 2
  },
  "iPod touch (4th generation)": {
    "name": "iPod touch (4th generation)",
    "type": "iPod touch",
    "devices": [
      "iPod4,1"
    ],
    "order": 3
  },
  "iPod touch (5th generation)": {
    "name": "iPod touch (5th generation)",
    "type": "iPod touch",
    "devices": [
      "iPod5,1"
    ],
    "order": 4
  },
  "iPod touch (6th generation)": {
    "name": "iPod touch (6th generation)",
    "type": "iPod touch",
    "devices": [
      "iPod7,1"
    ],
    "order": 5
  },
  "iPod touch (7th generation)": {
    "name": "iPod touch (7th generation)",
    "type": "iPod touch",
    "devices": [
      "iPod9,1"
    ],
    "order": 6
  },
  "Pro Display XDR": {
    "name": "Pro Display XDR",
    "type": "Display",
    "devices": [
      "iSim1,1"
    ],
    "order": 0
  }
}